dictdaora/__init__.py
dictdaora/dictdaora.py
dictdaora/py.typed
dictdaora/tests/test_dictdaora.py
dictdaora-0.0.2.dist-info/LICENSE
dictdaora-0.0.2.dist-info/WHEEL
dictdaora-0.0.2.dist-info/METADATA
dictdaora-0.0.2.dist-info/RECORD
